{"song":{"song":"Milf JP Version","bpm":180.0,"needsVoices":true,"player1":"bf-car-neko","player2":"mom-car-neko","gfVersion":"gf-car-neko","stage":"limo","speed":1.8,"notes":[{"lengthInSteps":16,"mustHitSection":true,"sectionNotes":[]},{"lengthInSteps":16,"mustHitSection":true,"sectionNotes":[]},{"lengthInSteps":16,"mustHitSection":false,"sectionNotes":[[2666.66675,3,0.0],[3000.0,3,0.0],[3333.3335,1,0.0],[3666.66675,1,0.0]]},{"lengthInSteps":16,"mustHitSection":false,"sectionNotes":[[4000.0,2,0.0],[4333.3335,0,0.0],[4500.0,1,0.0],[5000.0,1,0.0]]},{"lengthInSteps":16,"mustHitSection":false,"sectionNotes":[[5333.3335,3,0.0],[5666.667,3,0.0],[6000.0,1,0.0],[6333.3335,1,0.0]]},{"lengthInSteps":16,"mustHitSection":false,"sectionNotes":[[6666.667,2,0.0],[7000.0,1,0.0],[7333.3335,2,0.0],[7500.0,0,0.0],[7666.667,1,0.0],[7833.3335,2,0.0]]},{"lengthInSteps":16,"mustHitSection":true,"sectionNotes":[[8000.0,3,0.0],[8333.334,3,0.0],[8666.667,1,0.0],[9000.0,1,0.0]]},{"lengthInSteps":16,"mustHitSection":true,"sectionNotes":[[9333.334,2,0.0],[9666.667,0,0.0],[9833.334,1,0.0],[10333.334,1,0.0]]},{"lengthInSteps":16,"mustHitSection":true,"sectionNotes":[[10666.667,3,0.0],[11000.0,3,0.0],[11333.334,1,0.0],[11666.667,1,0.0]]},{"lengthInSteps":16,"mustHitSection":true,"sectionNotes":[[12000.0,7,166.666672],[12000.0,2,0.0],[12333.334,6,166.666672],[12333.334,1,0.0],[12666.667,2,0.0],[12666.667,7,166.666672],[12833.334,0,0.0],[13000.0,5,166.666672],[13000.0,1,0.0],[13166.667,2,0.0]]},{"lengthInSteps":16,"mustHitSection":false,"sectionNotes":[[13666.667,3,250.0],[14000.0,1,250.0]]},{"lengthInSteps":16,"mustHitSection":false,"sectionNotes":[[14666.667,1,250.0],[15333.334,1,250.0],[15666.667,0,250.0]]},{"lengthInSteps":16,"mustHitSection":false,"sectionNotes":[[16000.0,1,250.0],[16666.668,1,250.0],[17000.0,2,250.0]]},{"lengthInSteps":16,"mustHitSection":false,"sectionNotes":[[17333.334,3,666.6667]]},{"lengthInSteps":16,"mustHitSection":true,"sectionNotes":[[19000.0,2,250.0],[19333.334,3,250.0]]},{"lengthInSteps":16,"mustHitSection":true,"sectionNotes":[[20000.0,2,250.0],[20666.668,0,250.0]]},{"lengthInSteps":16,"mustHitSection":true,"sectionNotes":[[21333.334,3,250.0],[22000.0,3,250.0],[22333.334,1,250.0]]},{"lengthInSteps":16,"mustHitSection":true,"sectionNotes":[[22666.668,2,333.333344],[23333.334,5,0.0],[23333.334,3,333.333344],[23666.668,6,0.0]]},{"lengthInSteps":16,"mustHitSection":false,"sectionNotes":[[24000.0,5,1000.0],[24000.0,0,0.0],[24666.668,0,0.0]]},{"lengthInSteps":16,"mustHitSection":false,"sectionNotes":[[25333.334,0,0.0],[25666.668,3,0.0],[26000.0,0,250.0],[26333.334,1,250.0]]},{"lengthInSteps":16,"mustHitSection":false,"sectionNotes":[[26666.668,0,0.0],[27333.334,0,0.0]]},{"lengthInSteps":16,"mustHitSection":false,"sectionNotes":[[28000.0,3,0.0],[28333.334,0,0.0],[28666.668,3,250.0]]},{"lengthInSteps":16,"mustHitSection":true,"sectionNotes":[[29333.334,0,0.0],[30000.0,0,0.0]]},{"lengthInSteps":16,"mustHitSection":true,"sectionNotes":[[30666.668,0,0.0],[31000.0,3,0.0],[31333.334,0,250.0],[31833.334,0,0.0]]},{"lengthInSteps":16,"mustHitSection":true,"sectionNotes":[[32333.334,3,0.0],[32666.668,1,250.0],[33000.0,2,250.0]]},{"lengthInSteps":16,"mustHitSection":true,"sectionNotes":[[33333.3359,0,0.0],[34000.0,0,0.0]]},{"lengthInSteps":16,"mustHitSection":false,"sectionNotes":[[34666.668,0,0.0],[35333.3359,0,0.0]]},{"lengthInSteps":16,"mustHitSection":false,"sectionNotes":[[36000.0,0,0.0],[36333.3359,3,0.0],[36666.668,0,250.0],[37000.0,1,250.0]]},{"lengthInSteps":16,"mustHitSection":false,"sectionNotes":[[37333.3359,0,0.0],[38000.0,0,0.0]]},{"lengthInSteps":16,"mustHitSection":false,"sectionNotes":[[38666.668,3,0.0],[39000.0,0,0.0],[39333.3359,3,250.0]]},{"lengthInSteps":16,"mustHitSection":true,"sectionNotes":[[40000.0,0,0.0],[40666.668,0,0.0]]},{"lengthInSteps":16,"mustHitSection":true,"sectionNotes":[[41333.3359,0,0.0],[41666.668,3,0.0],[42000.0,0,250.0],[42500.0,0,0.0]]},{"lengthInSteps":16,"mustHitSection":true,"sectionNotes":[[43333.3359,1,250.0],[43666.668,2,250.0]]},{"lengthInSteps":16,"mustHitSection":true,"sectionNotes":[[44000.0,0,0.0],[44666.668,0,0.0]]},{"lengthInSteps":16,"mustHitSection":false,"sectionNotes":[[45666.668,3,250.0],[46000.0,1,250.0]]},{"lengthInSteps":16,"mustHitSection":false,"sectionNotes":[[46666.668,1,250.0],[47333.3359,1,250.0],[47666.668,0,250.0]]},{"lengthInSteps":16,"mustHitSection":false,"sectionNotes":[[48000.0,1,250.0],[48666.668,1,250.0],[49000.0,2,250.0]]},{"lengthInSteps":16,"mustHitSection":false,"sectionNotes":[[49333.3359,3,666.6667]]},{"lengthInSteps":16,"mustHitSection":true,"sectionNotes":[[51000.0,0,250.0],[51333.3359,2,250.0]]},{"lengthInSteps":16,"mustHitSection":true,"sectionNotes":[[52000.0,2,250.0],[52666.668,0,250.0],[53000.0,2,250.0]]},{"lengthInSteps":16,"mustHitSection":true,"sectionNotes":[[53333.3359,3,250.0],[54000.0,3,250.0],[54333.3359,1,250.0]]},{"lengthInSteps":16,"mustHitSection":true,"sectionNotes":[[54666.668,2,333.333344],[55333.3359,3,333.333344]]},{"lengthInSteps":16,"mustHitSection":false,"sectionNotes":[[56000.0,5,1000.0],[56333.3359,3,250.0],[56666.668,1,250.0]]},{"lengthInSteps":16,"mustHitSection":false,"sectionNotes":[[57333.3359,1,250.0],[58000.0,1,250.0],[58333.3359,0,250.0]]},{"lengthInSteps":16,"mustHitSection":false,"sectionNotes":[[58666.668,1,250.0],[59333.3359,1,250.0],[59666.668,2,250.0]]},{"lengthInSteps":16,"mustHitSection":false,"sectionNotes":[[60000.0,3,666.6667]]},{"lengthInSteps":16,"mustHitSection":false,"sectionNotes":[[61666.668,0,250.0],[62000.0,2,250.0]]},{"lengthInSteps":16,"mustHitSection":false,"sectionNotes":[[62666.668,2,250.0],[63333.3359,0,250.0],[63666.668,1,250.0]]},{"lengthInSteps":16,"mustHitSection":false,"sectionNotes":[[64000.0,3,500.0],[64666.668,2,500.0]]},{"lengthInSteps":16,"mustHitSection":false,"sectionNotes":[[66000.0,1,0.0]]},{"lengthInSteps":16,"mustHitSection":false,"sectionNotes":[[66666.67,0,0.0],[67333.3359,0,0.0]]},{"lengthInSteps":16,"mustHitSection":false,"sectionNotes":[[68000.0,0,0.0],[68333.3359,3,0.0],[68666.67,0,250.0],[69000.0,1,250.0]]},{"lengthInSteps":16,"mustHitSection":false,"sectionNotes":[[69333.3359,0,0.0],[70000.0,0,0.0]]},{"lengthInSteps":16,"mustHitSection":false,"sectionNotes":[[70666.67,3,0.0],[71000.0,0,0.0],[71333.3359,3,250.0]]},{"lengthInSteps":16,"mustHitSection":true,"sectionNotes":[[72000.0,0,0.0],[72666.67,0,0.0]]},{"lengthInSteps":16,"mustHitSection":true,"sectionNotes":[[73333.3359,0,0.0],[73666.67,3,0.0],[74000.0,0,250.0],[74500.0,0,0.0]]},{"lengthInSteps":16,"mustHitSection":true,"sectionNotes":[[75000.0,3,0.0],[75333.3359,1,250.0],[75666.67,2,250.0]]},{"lengthInSteps":16,"mustHitSection":true,"sectionNotes":[[76000.0,0,0.0],[76666.67,0,0.0]]},{"lengthInSteps":16,"mustHitSection":false,"sectionNotes":[[77333.3359,4,0.0],[77333.3359,0,0.0],[78000.0,4,0.0],[78000.0,0,0.0]]},{"lengthInSteps":16,"mustHitSection":false,"sectionNotes":[[78666.67,0,0.0],[78666.67,4,0.0],[79000.0,3,0.0],[79000.0,7,0.0],[79333.3359,4,0.0],[79333.3359,0,0.0],[79666.67,1,0.0],[79666.67,5,0.0]]},{"lengthInSteps":16,"mustHitSection":false,"sectionNotes":[[80000.0,4,0.0],[80000.0,0,0.0],[80666.67,4,0.0],[80666.67,0,0.0],[81000.0,0,0.0],[81000.0,4,0.0]]},{"lengthInSteps":16,"mustHitSection":false,"sectionNotes":[[81333.3359,3,0.0],[81333.3359,7,0.0],[81666.67,0,0.0],[81666.67,4,0.0],[82000.0,7,250.0],[82000.0,3,250.0]]},{"lengthInSteps":16,"mustHitSection":true,"sectionNotes":[[82666.67,4,250.0],[82666.67,0,0.0],[83333.3359,7,250.0],[83333.3359,0,0.0],[83666.67,5,250.0]]},{"lengthInSteps":16,"mustHitSection":true,"sectionNotes":[[84000.0,0,0.0],[84000.0,6,250.0],[84333.3359,3,0.0],[84666.67,7,250.0],[84666.67,0,250.0],[85000.0,5,250.0],[85166.67,0,0.0]]},{"lengthInSteps":16,"mustHitSection":true,"sectionNotes":[[85333.3359,4,250.0],[85500.0,0,250.0],[86000.0,3,250.0],[86000.0,4,250.0],[86333.3359,1,250.0]]},{"lengthInSteps":16,"mustHitSection":true,"sectionNotes":[[86666.67,6,250.0],[86666.67,0,0.0],[87333.3359,6,250.0],[87333.3359,0,0.0],[87666.67,5,250.0]]},{"lengthInSteps":16,"mustHitSection":false,"sectionNotes":[[88000.0,3,0.0],[88333.3359,3,0.0],[88666.67,1,0.0],[89000.0,1,0.0]]},{"lengthInSteps":16,"mustHitSection":false,"sectionNotes":[[89500.0,0,0.0],[89833.3359,0,0.0],[90333.3359,2,0.0]]},{"lengthInSteps":16,"mustHitSection":false,"sectionNotes":[[90666.67,3,0.0],[91000.0,3,0.0],[91333.3359,1,0.0],[91666.67,1,0.0]]},{"lengthInSteps":16,"mustHitSection":false,"sectionNotes":[[92000.0,2,0.0],[92333.3359,1,0.0],[92666.67,2,0.0],[92833.3359,0,0.0],[93000.0,1,0.0],[93166.67,2,0.0]]},{"lengthInSteps":16,"mustHitSection":true,"sectionNotes":[[93333.3359,3,0.0],[93666.67,3,0.0],[94000.0,1,0.0],[94333.3359,1,0.0]]},{"lengthInSteps":16,"mustHitSection":true,"sectionNotes":[[94833.3359,0,0.0],[95166.67,0,0.0],[95666.67,2,0.0]]},{"lengthInSteps":16,"mustHitSection":true,"sectionNotes":[[96000.0,3,0.0],[96000.0,7,0.0],[96333.3359,3,0.0],[96333.3359,7,0.0],[96666.67,5,0.0],[96666.67,1,0.0],[97000.0,5,0.0],[97000.0,1,0.0]]},{"lengthInSteps":16,"mustHitSection":true,"sectionNotes":[[97333.3359,6,0.0],[97333.3359,2,0.0],[97666.67,1,0.0],[97666.67,5,0.0],[98000.0,6,0.0],[98000.0,2,0.0]]},{"lengthInSteps":16,"mustHitSection":false,"sectionNotes":[[98666.67,2,666.6667],[99833.3359,3,250.0]]},{"lengthInSteps":16,"mustHitSection":false,"sectionNotes":[[100500.0,2,250.0],[100833.336,0,0.0],[101166.672,1,250.0]]},{"lengthInSteps":16,"mustHitSection":false,"sectionNotes":[[101666.672,1,250.0],[102000.0,2,250.0],[102333.336,0,0.0]]},{"lengthInSteps":16,"mustHitSection":false,"sectionNotes":[[102666.672,3,0.0],[103000.0,0,0.0],[103333.336,3,0.0],[103500.0,2,0.0],[103666.672,0,0.0],[103833.336,1,0.0]]},{"lengthInSteps":16,"mustHitSection":true,"sectionNotes":[[104000.0,2,666.6667],[104000.0,6,666.6667],[105166.672,3,250.0]]},{"lengthInSteps":16,"mustHitSection":true,"sectionNotes":[[105833.336,2,250.0],[106166.672,0,0.0],[106500.0,1,250.0]]},{"lengthInSteps":16,"mustHitSection":true,"sectionNotes":[[107000.0,1,250.0],[107333.336,2,250.0],[107666.672,0,0.0]]},{"lengthInSteps":16,"mustHitSection":true,"sectionNotes":[[108000.0,3,0.0],[108333.336,0,0.0],[108666.672,3,0.0],[108833.336,2,0.0],[109000.0,0,0.0],[109166.672,1,0.0]]},{"lengthInSteps":16,"mustHitSection":false,"sectionNotes":[[109333.336,3,0.0],[109666.672,3,0.0],[110000.0,1,0.0],[110333.336,1,0.0]]},{"lengthInSteps":16,"mustHitSection":false,"sectionNotes":[[110666.672,2,0.0],[111000.0,0,0.0],[111166.672,1,0.0],[111666.672,1,0.0]]},{"lengthInSteps":16,"mustHitSection":false,"sectionNotes":[[112000.0,3,0.0],[112333.336,3,0.0],[112666.672,1,0.0],[113000.0,1,0.0]]},{"lengthInSteps":16,"mustHitSection":false,"sectionNotes":[[113333.336,2,0.0],[113666.672,1,0.0],[114000.0,2,0.0],[114166.672,0,0.0],[114333.336,1,0.0],[114500.0,2,0.0]]},{"lengthInSteps":16,"mustHitSection":true,"sectionNotes":[[114666.672,3,0.0],[115000.0,3,0.0],[115333.336,1,0.0],[115666.672,1,0.0]]},{"lengthInSteps":16,"mustHitSection":true,"sectionNotes":[[116000.0,2,0.0],[116333.336,0,0.0],[116500.0,1,0.0],[117000.0,1,0.0]]},{"lengthInSteps":16,"mustHitSection":true,"sectionNotes":[[117333.336,3,0.0],[117666.672,3,0.0],[118000.0,1,0.0],[118333.336,1,0.0]]},{"lengthInSteps":16,"mustHitSection":true,"sectionNotes":[[118666.672,2,0.0],[119000.0,1,0.0],[119333.336,2,333.333344],[119666.672,5,166.666672]]}]},"generatedBy":"SNIFF ver.7 - KE-HQ EDITION V3 (NOW WITH MINES?!?!!)"}